socx/__init__.py
socx/__main__.py
socx/cli/__init__.py
socx/cli/_cli.py
socx/cli/_jinja.py
socx/cli/callbacks.py
socx/cli/cfg.py
socx/cli/cli.py
socx/cli/params.py
socx/config/__init__.py
socx/config/_config.py
socx/config/_settings.py
socx/config/converters.py
socx/config/encoders.py
socx/config/formatters.py
socx/config/serializers.py
socx/config/validators.py
socx/config/schema/__init__.py
socx/config/schema/plugin.py
socx/core/__init__.py
socx/core/_paths.py
socx/core/encoder.py
socx/core/enums.py
socx/core/metadata.py
socx/core/paths.py
socx/core/serializer.py
socx/core/types.py
socx/io/__init__.py
socx/io/console.py
socx/io/decorators.py
socx/io/log.py
socx/patterns/__init__.py
socx/patterns/mixins/__init__.py
socx/patterns/mixins/proxy.py
socx/patterns/mixins/uid.py
socx/patterns/singleton/__init__.py
socx/patterns/singleton/singleton.py
socx/patterns/visitor/__init__.py
socx/patterns/visitor/protocol.py
socx/patterns/visitor/traversal.py
socx/regression/__init__.py
socx/regression/regression.py
socx/regression/status.py
socx/regression/test.py
socx/regression/validator.py
socx/static/settings/cli.yaml
socx/static/settings/console.yaml
socx/static/settings/git.yaml
socx/static/settings/plugins.yaml
socx/static/settings/regression.yaml
socx/static/settings/rich_click.yaml
socx/static/settings/settings.yaml
socx/static/sql/socx.sql
socx/utils/__init__.py
socx/utils/decorators.py
socx_plugins/config/__init__.py
socx_plugins/config/_config.py
socx_plugins/config/edit.py
socx_plugins/git/__init__.py
socx_plugins/git/arguments.py
socx_plugins/git/callbacks.py
socx_plugins/git/cli.py
socx_plugins/git/manifest.py
socx_plugins/git/renderables.py
socx_plugins/git/summary.py
socx_plugins/git/utils.py
socx_plugins/plugin/__init__.py
socx_plugins/plugin/example.py
socx_plugins/plugin/schema.py
socx_plugins/rgr/__init__.py
socx_plugins/rgr/_rgr.py
socx_plugins/rgr/callbacks.py
socx_plugins/rgr/rgr.py
socx_plugins/version/__init__.py
socx_plugins/version/__main__.py
socx_cli-0.11.1.dist-info/METADATA
socx_cli-0.11.1.dist-info/WHEEL
socx_cli-0.11.1.dist-info/entry_points.txt
socx_cli-0.11.1.dist-info/licenses/LICENSE
socx_cli-0.11.1.dist-info/RECORD
