Metadata-Version: 2.4
Name: socx-cli
Version: 0.11.1
Summary: System on chip verification and tooling infrastructure.
Project-URL: Issues, https://github.com/sagikimhi/socx-cli/issues
Project-URL: Homepage, https://sagikimhi.dev/socx-cli
Project-URL: Changelog, https://sagikimhi.dev/socx-cli/changelog
Project-URL: Repository, https://github.com/sagikimhi/socx-cli
Project-URL: Discussions, https://github.com/sagikimhi/socx-cli/discussions
Project-URL: Documentation, https://sagikimhi.dev/socx-cli
Author-email: Sagi Kimhi <sagi.kim5@gmail.com>
Maintainer-email: Sagi Kimhi <sagi.kim5@gmail.com>
License-Expression: Apache-2.0
License-File: LICENSE
Classifier: Development Status :: 2 - Pre-Alpha
Classifier: Environment :: Console
Classifier: Environment :: Plugins
Classifier: Intended Audience :: Developers
Classifier: License :: OSI Approved :: Apache Software License
Classifier: Programming Language :: Python
Classifier: Programming Language :: Python :: 3
Classifier: Programming Language :: Python :: 3 :: Only
Classifier: Programming Language :: Python :: 3.10
Classifier: Programming Language :: Python :: 3.11
Classifier: Programming Language :: Python :: 3.12
Classifier: Programming Language :: Python :: 3.13
Classifier: Programming Language :: Python :: 3.14
Classifier: Topic :: Documentation
Classifier: Topic :: Scientific/Engineering :: Electronic Design Automation (EDA)
Classifier: Topic :: Software Development
Classifier: Topic :: Utilities
Requires-Python: >=3.10
Requires-Dist: click
Requires-Dist: copier~=9.11
Requires-Dist: dynaconf
Requires-Dist: gitpython
Requires-Dist: hoptex
Requires-Dist: jinja2
Requires-Dist: paramiko
Requires-Dist: pip
Requires-Dist: platformdirs
Requires-Dist: plumbum
Requires-Dist: prompt-toolkit>=3.0.52
Requires-Dist: psutil
Requires-Dist: pydantic
Requires-Dist: python-box[ruamel-yaml,toml]~=7.0
Requires-Dist: rich
Requires-Dist: rich-click
Requires-Dist: sh~=2.2
Requires-Dist: textual
Requires-Dist: textual-speedups
Requires-Dist: typer~=0.19
Requires-Dist: uv
Requires-Dist: werkzeug>=3.1.4
